mw/__init__.py
mw/__main__.py
mw/app.py
mw/commands.py
mw/display.py
mw/stack.py
mw/types.py
mw-0.4.0.data/data/share/man/man1/mw.1
mw-0.4.0.dist-info/entry_points.txt
mw-0.4.0.dist-info/WHEEL
mw-0.4.0.dist-info/METADATA
mw-0.4.0.dist-info/RECORD
