Metadata-Version: 2.1
Name: mw
Version: 0.4.0
Summary: mw is an audio sample editor for the terminal.
Keywords: waveform,metadata,audio,console
Author-email: Jamie Hardt <jamiehardt@me.com>
Requires-Python: ~=3.8
Classifier: Topic :: Multimedia
Classifier: Topic :: Multimedia :: Sound/Audio
Classifier: Development Status :: 4 - Beta
Classifier: Environment :: Console
Classifier: License :: OSI Approved :: BSD License
Classifier: Programming Language :: Python :: 3.8
Classifier: Programming Language :: Python :: 3.9
Classifier: Programming Language :: Python :: 3.10
Classifier: Programming Language :: Python :: 3.11
Requires-Dist: numpy ~= 1.24.3
Requires-Dist: parsimonious ~= 0.10.0
Requires-Dist: pydub ~= 0.25.1
Requires-Dist: apeek ~= 0.1.1
Requires-Dist: gnureadline ~= 8.1.2
Requires-Dist: sphinx >= 5.3.0 ; extra == "doc"
Requires-Dist: sphinx_rtd_theme >= 1.1.1 ; extra == "doc"
Project-URL: Home, https://github.com/iluvcapra/mw
Project-URL: Issues, https://github.com/iluvcapra/mw/issues
Project-URL: Source, https://github.com/iluvcapra/mw.git
Provides-Extra: doc
